{
    "hud-text.desc_sick": "Вы простудились!",
    "hud-text.desc_hot": "Жаркие показатели температуры на улице изнуряют вас намного сильнее, чем обычно.",
    "hud-text.desc_cold": "Сильный холод на улице утомляет вас намного быстрее,чем обычно.",
    "hud-text.desc_turntheheaton": "Холод просочился сквозь стены дома, изматывая и снижая вашу физическую активность...",
    "hud-text.desc_inclement": "Ненастная погода сильно опечалила вас, буквально до тошноты...",
    "hud-text.desc_blizzard": "Ветер и снег пробрали вас до мозга костей, постепенно снижая реакцию и скорость...",
    "hud-text.desc_wampa": "Сильнейшая метель катастрофически истощает вас, заметно снижая вашу силу и скорость...", 
    "hud-text.desc_darude": "Песчаная буря, сыплящая прямо навстречу, практически ослепила вас, постепенно высасывая силу и скорость...",
    "hud-text.desc_freeze": "Из-за холодной погоды на улице, вы чувствуете утомлённость и легкую сонливость.",
    "hud-text.desc_flu": "Вы подхватили сильную простуду из-за непогоды. Лучше всего поскорее приобретите и примите какое-нибудь лекарство!",
    "hud-text.desc_cold_removed": "Вы чувствуете, как лекарство очищает организм от болезни и приводит в норму физическую форму.",
    "hud-text.desc_bathHouse":  "Приём горячих водных процедур как бальзам на душу - вы чувствуете себя намного лучше.",
    "hud-text.desc_HeatOn":  "Холод просачивается сквозь стены вашего дома; вы просто обязаны включить камин, дабы не околеть..."
  }
